ensure_sops/__init__.py
ensure_sops/__main__.py
ensure_sops/enums.py
ensure_sops/exceptions.py
ensure_sops/formats.py
ensure_sops/main.py
ensure_sops/validator.py
ensure_sops-0.1.2.dist-info/entry_points.txt
ensure_sops-0.1.2.dist-info/LICENSE
ensure_sops-0.1.2.dist-info/WHEEL
ensure_sops-0.1.2.dist-info/METADATA
ensure_sops-0.1.2.dist-info/RECORD
