Metadata-Version: 2.1
Name: ensure-sops
Version: 0.1.2
Summary: Check if your files are encrypted with Mozilla SOPS or not. Can act as pre-commit hook as well.
License: BSD 3-Clause License
Author: Engineering Team at Tacto Technology GmbH.
Author-email: engineering@tacto.ai
Requires-Python: >=3.7,<3.11
Classifier: License :: Other/Proprietary License
Classifier: Programming Language :: Python :: 3
Classifier: Programming Language :: Python :: 3.10
Classifier: Programming Language :: Python :: 3.7
Classifier: Programming Language :: Python :: 3.8
Classifier: Programming Language :: Python :: 3.9
Requires-Dist: ordered-set (>=4.1.0,<5.0.0)
Requires-Dist: python-dotenv (>=0.20.0,<0.21.0)
Requires-Dist: ruamel.yaml (>=0.17.21,<0.18.0)
